{
"product": {
    "title": "TITLE HERE",
    "body_html": "DESCRIPTION HERE",
    "vendor": "VENDOR HERE",
    "product_type": "PRODUCT TYPE HERE",
    "variants": {
        "option1": "Default",
        "price": "PRICE HERE"
    },
    "images": {
        "src": "LINK TO IMAGE HERE"
    }
},
"product": {
    "title": "TITLE HERE",
    "body_html": "DESCRIPTION HERE",
    "vendor": "VENDOR HERE",
    "product_type": "PRODUCT TYPE HERE",
    "variants": {
        "option1": "Default",
        "price": "PRICE HERE"
    },
    "images": {
        "src": "LINK TO IMAGE HERE"
    }
},
"product": {
    "title": "TITLE HERE",
    "body_html": "DESCRIPTION HERE",
    "vendor": "VENDOR HERE",
    "product_type": "PRODUCT TYPE HERE",
    "variants": {
        "option1": "Default",
        "price": "PRICE HERE"
    },
    "images": {
        "src": "LINK TO IMAGE HERE"
    }
}
}
